filter_openapi/__init__.py
filter_openapi/__main__.py
filter_openapi/settings.py
filter_openapi/actions/__init__.py
filter_openapi/actions/filter_endpoints.py
filter_openapi/actions/filter_paths_by_tags.py
filter_openapi/actions/filter_schemas.py
filter_openapi/actions/filter_tags_list.py
filter_openapi/actions/remove_properties.py
filter_openapi-0.1.2.dist-info/METADATA
filter_openapi-0.1.2.dist-info/WHEEL
filter_openapi-0.1.2.dist-info/licenses/LICENSE
filter_openapi-0.1.2.dist-info/RECORD
