Metadata-Version: 2.4
Name: filter-openapi
Version: 0.1.2
Summary: Generates a valid OpenAPI spec from source spec. Various options for filtering out parts of the spec you don't want.
Author-email: Greg Rutz <greg80303@gmail.com>
License-File: LICENSE
Requires-Python: >=3.10
Requires-Dist: pydantic
Requires-Dist: pyyaml
